github_fine_grained_token_client/__init__.py
github_fine_grained_token_client/abstract_http_session.py
github_fine_grained_token_client/app.py
github_fine_grained_token_client/asynchronous_client.py
github_fine_grained_token_client/cli.py
github_fine_grained_token_client/common.py
github_fine_grained_token_client/credentials.py
github_fine_grained_token_client/dev.py
github_fine_grained_token_client/permissions.py
github_fine_grained_token_client/persisting_http_session.py
github_fine_grained_token_client/two_factor_authentication.py
github_fine_grained_token_client/utils/__init__.py
github_fine_grained_token_client/utils/asyncio.py
github_fine_grained_token_client/utils/bs4.py
github_fine_grained_token_client/utils/sequences.py
github_fine_grained_token_client-1.0.0.dist-info/entry_points.txt
github_fine_grained_token_client-1.0.0.dist-info/LICENSE
github_fine_grained_token_client-1.0.0.dist-info/WHEEL
github_fine_grained_token_client-1.0.0.dist-info/METADATA
github_fine_grained_token_client-1.0.0.dist-info/RECORD
