Metadata-Version: 2.1
Name: github-fine-grained-token-client
Version: 1.0.0
Summary: Library and CLI tool for creating fine-grained GitHub tokens
Home-page: https://smheidrich.gitlab.io/github-fine-grained-token-client/
Author: smheidrich
Author-email: smheidrich@weltenfunktion.de
Requires-Python: >=3.10,<4.0
Classifier: Programming Language :: Python :: 3
Classifier: Programming Language :: Python :: 3.10
Classifier: Programming Language :: Python :: 3.11
Provides-Extra: all
Provides-Extra: cli
Requires-Dist: aiohttp[all] (>=3.8.3,<4.0.0)
Requires-Dist: beautifulsoup4 (>=4.11.1,<5.0.0)
Requires-Dist: dateparser (>=1.1.6,<2.0.0)
Requires-Dist: enum-properties (>=1.3.3,<2.0.0)
Requires-Dist: keyring (>=23.13.1,<24.0.0); extra == "all" or extra == "cli"
Requires-Dist: python-dateutil (>=2.8.2,<3.0.0)
Requires-Dist: typer (>=0.7.0,<0.8.0); extra == "all" or extra == "cli"
Requires-Dist: yachalk (>=0.1.5,<0.2.0); extra == "all" or extra == "cli"
Project-URL: Documentation, https://smheidrich.gitlab.io/github-fine-grained-token-client/
Project-URL: Repository, https://gitlab.com/smheidrich/github-fine-grained-token-client
